mumema/__init__.py
mumema/__main__.py
mumema/formats.py
mumema-1.1.1.dist-info/entry_points.txt
mumema-1.1.1.dist-info/LICENSE
mumema-1.1.1.dist-info/WHEEL
mumema-1.1.1.dist-info/METADATA
mumema-1.1.1.dist-info/RECORD
