Metadata-Version: 2.1
Name: mumema
Version: 1.1.1
Summary: Music Metadata Manager
Keywords: scripts,commandline
Author-email: Johannes Krattenmacher <mumema@dev.krateng.ch>
Requires-Python: >=3.6
Classifier: Programming Language :: Python :: 3
Classifier: License :: OSI Approved :: GNU General Public License v3 (GPLv3)
Classifier: Operating System :: OS Independent
Requires-Dist: doreah >= 1.6.11
Requires-Dist: unidecode
Project-URL: repository, https://github.com/krateng/mumema
